{"nodes": [{"id": "s_diaster_wholesale_src_pages_reports_currentstockreport_tsx", "label": "CurrentStockReport.tsx", "file_type": "code", "source_file": "S:\\Diaster-Wholesale\\src\\pages\\reports\\CurrentStockReport.tsx", "source_location": "L1"}, {"id": "currentstockreport_loaddata", "label": "loadData()", "file_type": "code", "source_file": "S:\\Diaster-Wholesale\\src\\pages\\reports\\CurrentStockReport.tsx", "source_location": "L27"}, {"id": "currentstockreport_load", "label": "load()", "file_type": "code", "source_file": "S:\\Diaster-Wholesale\\src\\pages\\reports\\CurrentStockReport.tsx", "source_location": "L37"}, {"id": "currentstockreport_handlerefresh", "label": "handleRefresh()", "file_type": "code", "source_file": "S:\\Diaster-Wholesale\\src\\pages\\reports\\CurrentStockReport.tsx", "source_location": "L44"}, {"id": "currentstockreport_clampunits", "label": "clampUnits()", "file_type": "code", "source_file": "S:\\Diaster-Wholesale\\src\\pages\\reports\\CurrentStockReport.tsx", "source_location": "L55"}, {"id": "currentstockreport_getlocationstats", "label": "getLocationStats()", "file_type": "code", "source_file": "S:\\Diaster-Wholesale\\src\\pages\\reports\\CurrentStockReport.tsx", "source_location": "L62"}], "edges": [{"source": "s_diaster_wholesale_src_pages_reports_currentstockreport_tsx", "target": "react", "relation": "imports_from", "confidence": "EXTRACTED", "source_file": "S:\\Diaster-Wholesale\\src\\pages\\reports\\CurrentStockReport.tsx", "source_location": "L1", "weight": 1.0}, {"source": "s_diaster_wholesale_src_pages_reports_currentstockreport_tsx", "target": "s_diaster_wholesale_src_services_reportservice", "relation": "imports_from", "confidence": "EXTRACTED", "source_file": "S:\\Diaster-Wholesale\\src\\pages\\reports\\CurrentStockReport.tsx", "source_location": "L2", "weight": 1.0}, {"source": "s_diaster_wholesale_src_pages_reports_currentstockreport_tsx", "target": "s_diaster_wholesale_src_pages_reports_shared_reporttable", "relation": "imports_from", "confidence": "EXTRACTED", "source_file": "S:\\Diaster-Wholesale\\src\\pages\\reports\\CurrentStockReport.tsx", "source_location": "L3", "weight": 1.0}, {"source": "s_diaster_wholesale_src_pages_reports_currentstockreport_tsx", "target": "s_diaster_wholesale_src_pages_reports_shared_exportbar", "relation": "imports_from", "confidence": "EXTRACTED", "source_file": "S:\\Diaster-Wholesale\\src\\pages\\reports\\CurrentStockReport.tsx", "source_location": "L4", "weight": 1.0}, {"source": "s_diaster_wholesale_src_pages_reports_currentstockreport_tsx", "target": "lucide_react", "relation": "imports_from", "confidence": "EXTRACTED", "source_file": "S:\\Diaster-Wholesale\\src\\pages\\reports\\CurrentStockReport.tsx", "source_location": "L5", "weight": 1.0}, {"source": "s_diaster_wholesale_src_pages_reports_currentstockreport_tsx", "target": "s_diaster_wholesale_src_pages_reports_shared_reportkpicard", "relation": "imports_from", "confidence": "EXTRACTED", "source_file": "S:\\Diaster-Wholesale\\src\\pages\\reports\\CurrentStockReport.tsx", "source_location": "L6", "weight": 1.0}, {"source": "s_diaster_wholesale_src_pages_reports_currentstockreport_tsx", "target": "currentstockreport_loaddata", "relation": "contains", "confidence": "EXTRACTED", "source_file": "S:\\Diaster-Wholesale\\src\\pages\\reports\\CurrentStockReport.tsx", "source_location": "L27", "weight": 1.0}, {"source": "s_diaster_wholesale_src_pages_reports_currentstockreport_tsx", "target": "currentstockreport_load", "relation": "contains", "confidence": "EXTRACTED", "source_file": "S:\\Diaster-Wholesale\\src\\pages\\reports\\CurrentStockReport.tsx", "source_location": "L37", "weight": 1.0}, {"source": "s_diaster_wholesale_src_pages_reports_currentstockreport_tsx", "target": "currentstockreport_handlerefresh", "relation": "contains", "confidence": "EXTRACTED", "source_file": "S:\\Diaster-Wholesale\\src\\pages\\reports\\CurrentStockReport.tsx", "source_location": "L44", "weight": 1.0}, {"source": "s_diaster_wholesale_src_pages_reports_currentstockreport_tsx", "target": "currentstockreport_clampunits", "relation": "contains", "confidence": "EXTRACTED", "source_file": "S:\\Diaster-Wholesale\\src\\pages\\reports\\CurrentStockReport.tsx", "source_location": "L55", "weight": 1.0}, {"source": "s_diaster_wholesale_src_pages_reports_currentstockreport_tsx", "target": "currentstockreport_getlocationstats", "relation": "contains", "confidence": "EXTRACTED", "source_file": "S:\\Diaster-Wholesale\\src\\pages\\reports\\CurrentStockReport.tsx", "source_location": "L62", "weight": 1.0}, {"source": "currentstockreport_load", "target": "currentstockreport_loaddata", "relation": "calls", "confidence": "EXTRACTED", "source_file": "S:\\Diaster-Wholesale\\src\\pages\\reports\\CurrentStockReport.tsx", "source_location": "L38", "weight": 1.0}, {"source": "currentstockreport_handlerefresh", "target": "currentstockreport_loaddata", "relation": "calls", "confidence": "EXTRACTED", "source_file": "S:\\Diaster-Wholesale\\src\\pages\\reports\\CurrentStockReport.tsx", "source_location": "L46", "weight": 1.0}], "raw_calls": [{"caller_nid": "currentstockreport_loaddata", "callee": "getCurrentStockReportByLocation", "source_file": "S:\\Diaster-Wholesale\\src\\pages\\reports\\CurrentStockReport.tsx", "source_location": "L29"}, {"caller_nid": "currentstockreport_loaddata", "callee": "setLocationData", "source_file": "S:\\Diaster-Wholesale\\src\\pages\\reports\\CurrentStockReport.tsx", "source_location": "L30"}, {"caller_nid": "currentstockreport_loaddata", "callee": "error", "source_file": "S:\\Diaster-Wholesale\\src\\pages\\reports\\CurrentStockReport.tsx", "source_location": "L32"}, {"caller_nid": "currentstockreport_load", "callee": "setLoading", "source_file": "S:\\Diaster-Wholesale\\src\\pages\\reports\\CurrentStockReport.tsx", "source_location": "L39"}, {"caller_nid": "currentstockreport_handlerefresh", "callee": "setRefreshing", "source_file": "S:\\Diaster-Wholesale\\src\\pages\\reports\\CurrentStockReport.tsx", "source_location": "L45"}, {"caller_nid": "currentstockreport_handlerefresh", "callee": "setRefreshing", "source_file": "S:\\Diaster-Wholesale\\src\\pages\\reports\\CurrentStockReport.tsx", "source_location": "L47"}, {"caller_nid": "currentstockreport_clampunits", "callee": "max", "source_file": "S:\\Diaster-Wholesale\\src\\pages\\reports\\CurrentStockReport.tsx", "source_location": "L55"}, {"caller_nid": "currentstockreport_clampunits", "callee": "Number", "source_file": "S:\\Diaster-Wholesale\\src\\pages\\reports\\CurrentStockReport.tsx", "source_location": "L55"}, {"caller_nid": "currentstockreport_getlocationstats", "callee": "reduce", "source_file": "S:\\Diaster-Wholesale\\src\\pages\\reports\\CurrentStockReport.tsx", "source_location": "L64"}]}