{"nodes": [{"id": "s_diaster_wholesale_src_pages_customerspage_tsx", "label": "CustomersPage.tsx", "file_type": "code", "source_file": "S:\\Diaster-Wholesale\\src\\pages\\CustomersPage.tsx", "source_location": "L1"}, {"id": "customerspage_clearfilters", "label": "clearFilters()", "file_type": "code", "source_file": "S:\\Diaster-Wholesale\\src\\pages\\CustomersPage.tsx", "source_location": "L51"}, {"id": "customerspage_loadcustomers", "label": "loadCustomers()", "file_type": "code", "source_file": "S:\\Diaster-Wholesale\\src\\pages\\CustomersPage.tsx", "source_location": "L53"}, {"id": "customerspage_handleregister", "label": "handleRegister()", "file_type": "code", "source_file": "S:\\Diaster-Wholesale\\src\\pages\\CustomersPage.tsx", "source_location": "L69"}, {"id": "customerspage_handledeletecustomer", "label": "handleDeleteCustomer()", "file_type": "code", "source_file": "S:\\Diaster-Wholesale\\src\\pages\\CustomersPage.tsx", "source_location": "L93"}], "edges": [{"source": "s_diaster_wholesale_src_pages_customerspage_tsx", "target": "react", "relation": "imports_from", "confidence": "EXTRACTED", "source_file": "S:\\Diaster-Wholesale\\src\\pages\\CustomersPage.tsx", "source_location": "L1", "weight": 1.0}, {"source": "s_diaster_wholesale_src_pages_customerspage_tsx", "target": "lucide_react", "relation": "imports_from", "confidence": "EXTRACTED", "source_file": "S:\\Diaster-Wholesale\\src\\pages\\CustomersPage.tsx", "source_location": "L2", "weight": 1.0}, {"source": "s_diaster_wholesale_src_pages_customerspage_tsx", "target": "s_diaster_wholesale_src_lib_utils", "relation": "imports_from", "confidence": "EXTRACTED", "source_file": "S:\\Diaster-Wholesale\\src\\pages\\CustomersPage.tsx", "source_location": "L3", "weight": 1.0}, {"source": "s_diaster_wholesale_src_pages_customerspage_tsx", "target": "s_diaster_wholesale_src_components_modal", "relation": "imports_from", "confidence": "EXTRACTED", "source_file": "S:\\Diaster-Wholesale\\src\\pages\\CustomersPage.tsx", "source_location": "L4", "weight": 1.0}, {"source": "s_diaster_wholesale_src_pages_customerspage_tsx", "target": "s_diaster_wholesale_src_services_customerservice", "relation": "imports_from", "confidence": "EXTRACTED", "source_file": "S:\\Diaster-Wholesale\\src\\pages\\CustomersPage.tsx", "source_location": "L5", "weight": 1.0}, {"source": "s_diaster_wholesale_src_pages_customerspage_tsx", "target": "s_diaster_wholesale_src_types", "relation": "imports_from", "confidence": "EXTRACTED", "source_file": "S:\\Diaster-Wholesale\\src\\pages\\CustomersPage.tsx", "source_location": "L6", "weight": 1.0}, {"source": "s_diaster_wholesale_src_pages_customerspage_tsx", "target": "s_diaster_wholesale_src_components_confirmmodal", "relation": "imports_from", "confidence": "EXTRACTED", "source_file": "S:\\Diaster-Wholesale\\src\\pages\\CustomersPage.tsx", "source_location": "L7", "weight": 1.0}, {"source": "s_diaster_wholesale_src_pages_customerspage_tsx", "target": "react_router_dom", "relation": "imports_from", "confidence": "EXTRACTED", "source_file": "S:\\Diaster-Wholesale\\src\\pages\\CustomersPage.tsx", "source_location": "L8", "weight": 1.0}, {"source": "s_diaster_wholesale_src_pages_customerspage_tsx", "target": "framer_motion", "relation": "imports_from", "confidence": "EXTRACTED", "source_file": "S:\\Diaster-Wholesale\\src\\pages\\CustomersPage.tsx", "source_location": "L9", "weight": 1.0}, {"source": "s_diaster_wholesale_src_pages_customerspage_tsx", "target": "s_diaster_wholesale_src_components_animatednumber", "relation": "imports_from", "confidence": "EXTRACTED", "source_file": "S:\\Diaster-Wholesale\\src\\pages\\CustomersPage.tsx", "source_location": "L10", "weight": 1.0}, {"source": "s_diaster_wholesale_src_pages_customerspage_tsx", "target": "customerspage_clearfilters", "relation": "contains", "confidence": "EXTRACTED", "source_file": "S:\\Diaster-Wholesale\\src\\pages\\CustomersPage.tsx", "source_location": "L51", "weight": 1.0}, {"source": "s_diaster_wholesale_src_pages_customerspage_tsx", "target": "customerspage_loadcustomers", "relation": "contains", "confidence": "EXTRACTED", "source_file": "S:\\Diaster-Wholesale\\src\\pages\\CustomersPage.tsx", "source_location": "L53", "weight": 1.0}, {"source": "s_diaster_wholesale_src_pages_customerspage_tsx", "target": "customerspage_handleregister", "relation": "contains", "confidence": "EXTRACTED", "source_file": "S:\\Diaster-Wholesale\\src\\pages\\CustomersPage.tsx", "source_location": "L69", "weight": 1.0}, {"source": "s_diaster_wholesale_src_pages_customerspage_tsx", "target": "customerspage_handledeletecustomer", "relation": "contains", "confidence": "EXTRACTED", "source_file": "S:\\Diaster-Wholesale\\src\\pages\\CustomersPage.tsx", "source_location": "L93", "weight": 1.0}, {"source": "customerspage_handleregister", "target": "customerspage_loadcustomers", "relation": "calls", "confidence": "EXTRACTED", "source_file": "S:\\Diaster-Wholesale\\src\\pages\\CustomersPage.tsx", "source_location": "L87", "weight": 1.0}, {"source": "customerspage_handledeletecustomer", "target": "customerspage_loadcustomers", "relation": "calls", "confidence": "EXTRACTED", "source_file": "S:\\Diaster-Wholesale\\src\\pages\\CustomersPage.tsx", "source_location": "L100", "weight": 1.0}], "raw_calls": [{"caller_nid": "customerspage_clearfilters", "callee": "setFilterType", "source_file": "S:\\Diaster-Wholesale\\src\\pages\\CustomersPage.tsx", "source_location": "L51"}, {"caller_nid": "customerspage_clearfilters", "callee": "setSortBy", "source_file": "S:\\Diaster-Wholesale\\src\\pages\\CustomersPage.tsx", "source_location": "L51"}, {"caller_nid": "customerspage_clearfilters", "callee": "setSearchQuery", "source_file": "S:\\Diaster-Wholesale\\src\\pages\\CustomersPage.tsx", "source_location": "L51"}, {"caller_nid": "customerspage_loadcustomers", "callee": "setLoading", "source_file": "S:\\Diaster-Wholesale\\src\\pages\\CustomersPage.tsx", "source_location": "L55"}, {"caller_nid": "customerspage_loadcustomers", "callee": "getCustomers", "source_file": "S:\\Diaster-Wholesale\\src\\pages\\CustomersPage.tsx", "source_location": "L56"}, {"caller_nid": "customerspage_loadcustomers", "callee": "setCustomers", "source_file": "S:\\Diaster-Wholesale\\src\\pages\\CustomersPage.tsx", "source_location": "L57"}, {"caller_nid": "customerspage_loadcustomers", "callee": "error", "source_file": "S:\\Diaster-Wholesale\\src\\pages\\CustomersPage.tsx", "source_location": "L59"}, {"caller_nid": "customerspage_loadcustomers", "callee": "setLoading", "source_file": "S:\\Diaster-Wholesale\\src\\pages\\CustomersPage.tsx", "source_location": "L61"}, {"caller_nid": "customerspage_handleregister", "callee": "trim", "source_file": "S:\\Diaster-Wholesale\\src\\pages\\CustomersPage.tsx", "source_location": "L70"}, {"caller_nid": "customerspage_handleregister", "callee": "setFormError", "source_file": "S:\\Diaster-Wholesale\\src\\pages\\CustomersPage.tsx", "source_location": "L71"}, {"caller_nid": "customerspage_handleregister", "callee": "setFormLoading", "source_file": "S:\\Diaster-Wholesale\\src\\pages\\CustomersPage.tsx", "source_location": "L75"}, {"caller_nid": "customerspage_handleregister", "callee": "setFormError", "source_file": "S:\\Diaster-Wholesale\\src\\pages\\CustomersPage.tsx", "source_location": "L76"}, {"caller_nid": "customerspage_handleregister", "callee": "createCustomer", "source_file": "S:\\Diaster-Wholesale\\src\\pages\\CustomersPage.tsx", "source_location": "L77"}, {"caller_nid": "customerspage_handleregister", "callee": "setIsAddModalOpen", "source_file": "S:\\Diaster-Wholesale\\src\\pages\\CustomersPage.tsx", "source_location": "L78"}, {"caller_nid": "customerspage_handleregister", "callee": "setFormData", "source_file": "S:\\Diaster-Wholesale\\src\\pages\\CustomersPage.tsx", "source_location": "L79"}, {"caller_nid": "customerspage_handleregister", "callee": "setFormLoading", "source_file": "S:\\Diaster-Wholesale\\src\\pages\\CustomersPage.tsx", "source_location": "L89"}, {"caller_nid": "customerspage_handledeletecustomer", "callee": "setFormLoading", "source_file": "S:\\Diaster-Wholesale\\src\\pages\\CustomersPage.tsx", "source_location": "L96"}, {"caller_nid": "customerspage_handledeletecustomer", "callee": "setDeleteError", "source_file": "S:\\Diaster-Wholesale\\src\\pages\\CustomersPage.tsx", "source_location": "L97"}, {"caller_nid": "customerspage_handledeletecustomer", "callee": "archiveCustomer", "source_file": "S:\\Diaster-Wholesale\\src\\pages\\CustomersPage.tsx", "source_location": "L98"}, {"caller_nid": "customerspage_handledeletecustomer", "callee": "setDeleteTarget", "source_file": "S:\\Diaster-Wholesale\\src\\pages\\CustomersPage.tsx", "source_location": "L99"}, {"caller_nid": "customerspage_handledeletecustomer", "callee": "setDeleteError", "source_file": "S:\\Diaster-Wholesale\\src\\pages\\CustomersPage.tsx", "source_location": "L102"}, {"caller_nid": "customerspage_handledeletecustomer", "callee": "setFormLoading", "source_file": "S:\\Diaster-Wholesale\\src\\pages\\CustomersPage.tsx", "source_location": "L104"}]}